bln/__init__.py
bln/client.py
bln/exceptions.py
bln/queries.py
bln/pandas/__init__.py
bln/pandas/read_bln.py
bln/pandas/write_bln.py
bln-2.3.14.dist-info/licenses/LICENSE
bln-2.3.14.dist-info/METADATA
bln-2.3.14.dist-info/WHEEL
bln-2.3.14.dist-info/top_level.txt
bln-2.3.14.dist-info/RECORD
