Metadata-Version: 2.4
Name: bln
Version: 2.3.14
Summary: Python client for the biglocalnews.org API
Author-email: Big Local News <biglocalnews@stanford.edu>
License-Expression: Apache-2.0
Project-URL: Documentation, https://bln-python-client.readthedocs.io
Project-URL: Maintainer, https://github.com/biglocalnews
Project-URL: Source, https://github.com/biglocalnews/bln-python-client
Project-URL: Tracker, https://github.com/biglocalnews/bln-python-client/issues
Keywords: Big Local News,BLN,BLN API,Big Local News API
Classifier: Programming Language :: Python :: 3
Requires-Python: >=3.10
License-File: LICENSE
Requires-Dist: requests
Requires-Dist: retry2
Dynamic: license-file
